agently_format/__init__.py
agently_format/py.typed
agently_format/adapters/__init__.py
agently_format/adapters/custom_adapter.py
agently_format/adapters/deepseek_adapter.py
agently_format/adapters/doubao_adapter.py
agently_format/adapters/factory.py
agently_format/adapters/kimi_adapter.py
agently_format/adapters/model_adapter.py
agently_format/adapters/openai_adapter.py
agently_format/adapters/qianwen_adapter.py
agently_format/adapters/wenxin_adapter.py
agently_format/api/__init__.py
agently_format/api/app.py
agently_format/api/config.py
agently_format/api/middleware.py
agently_format/api/models.py
agently_format/api/routes.py
agently_format/core/__init__.py
agently_format/core/diff_engine.py
agently_format/core/event_system.py
agently_format/core/json_completer.py
agently_format/core/path_builder.py
agently_format/core/schemas.py
agently_format/core/streaming_parser.py
agently_format/types/__init__.py
agently_format/types/events.py
agently_format/types/models.py
agently_format/types/schemas.py
agentlyformat-2.0.0.dist-info/licenses/LICENSE
agentlyformat-2.0.0.dist-info/METADATA
agentlyformat-2.0.0.dist-info/WHEEL
agentlyformat-2.0.0.dist-info/entry_points.txt
agentlyformat-2.0.0.dist-info/top_level.txt
agentlyformat-2.0.0.dist-info/RECORD
