Metadata-Version: 2.4
Name: AgentlyFormat
Version: 2.0.0
Summary: 专注于大模型格式化输出结果的Python库，提供稳定可靠的JSON格式化解析能力 - v2.0.0重大更新：性能提升81%，架构全面重构
Author-email: ailijian <yeyubie@gmail.com>
License: Apache-2.0
Project-URL: Homepage, https://github.com/AgentEra/AgentlyFormat
Project-URL: Documentation, https://AgentlyFormat.readthedocs.io
Project-URL: Repository, https://github.com/AgentEra/AgentlyFormat
Project-URL: Bug Tracker, https://github.com/AgentEra/AgentlyFormat/issues
Keywords: llm,json,streaming,parser,ai,format,websocket,real-time,performance,schema-validation
Classifier: Development Status :: 5 - Production/Stable
Classifier: Intended Audience :: Developers
Classifier: License :: OSI Approved :: Apache Software License
Classifier: Operating System :: OS Independent
Classifier: Programming Language :: Python :: 3
Classifier: Programming Language :: Python :: 3.8
Classifier: Programming Language :: Python :: 3.9
Classifier: Programming Language :: Python :: 3.10
Classifier: Programming Language :: Python :: 3.11
Classifier: Programming Language :: Python :: 3.12
Classifier: Topic :: Software Development :: Libraries :: Python Modules
Classifier: Topic :: Scientific/Engineering :: Artificial Intelligence
Classifier: Topic :: Text Processing :: Markup
Classifier: Topic :: Internet :: WWW/HTTP :: HTTP Servers
Requires-Python: >=3.8
License-File: LICENSE
Requires-Dist: fastapi>=0.104.0
Requires-Dist: uvicorn[standard]>=0.24.0
Requires-Dist: pydantic>=2.5.0
Requires-Dist: httpx>=0.25.0
Requires-Dist: json5>=0.9.0
Requires-Dist: typing-extensions>=4.8.0
Requires-Dist: asyncio-mqtt>=0.13.0
Requires-Dist: python-multipart>=0.0.6
Requires-Dist: websockets>=12.0
Provides-Extra: dev
Requires-Dist: pytest>=7.4.0; extra == "dev"
Requires-Dist: pytest-asyncio>=0.21.0; extra == "dev"
Requires-Dist: pytest-mock>=3.12.0; extra == "dev"
Requires-Dist: pytest-cov>=4.1.0; extra == "dev"
Requires-Dist: black>=23.9.0; extra == "dev"
Requires-Dist: isort>=5.12.0; extra == "dev"
Requires-Dist: flake8>=6.1.0; extra == "dev"
Requires-Dist: mypy>=1.6.0; extra == "dev"
Requires-Dist: pre-commit>=3.5.0; extra == "dev"
Provides-Extra: docs
Requires-Dist: mkdocs>=1.5.0; extra == "docs"
Requires-Dist: mkdocs-material>=9.4.0; extra == "docs"
Requires-Dist: mkdocs-mermaid2-plugin>=1.1.0; extra == "docs"
Provides-Extra: test
Requires-Dist: pytest>=7.4.0; extra == "test"
Requires-Dist: pytest-asyncio>=0.21.0; extra == "test"
Requires-Dist: pytest-mock>=3.12.0; extra == "test"
Requires-Dist: pytest-cov>=4.1.0; extra == "test"
Dynamic: license-file
